{
  "Yousef Eid": { "ramadan": 0, "regular": 0 },
  "Nour Helal": { "ramadan": 0, "regular": 0 },
  "Engy Ahmed": { "ramadan": 0, "regular": 0 },
  "Deema": { "ramadan": 0, "regular": 0 },
  "Daniel Lewis": { "ramadan": 0, "regular": 0 },
  "Omar Mohamed": { "ramadan": 0, "regular": 0 },
  "Sameh Amnoun": { "ramadan": 0, "regular": 0 },
  "Aesha H.": { "ramadan": 0, "regular": 0 },
  "Ijaz Ahmed": { "ramadan": 0, "regular": 0 },
  "Muzamil S.": { "ramadan": 0, "regular": 0 },
  "Farah Eid": { "ramadan": 0, "regular": 0 }
}
